{
  "carvers": {},
  "downfall": 0.5,
  "effects": {
    "fog_color": 12771327,
    "foliage_color": 5667402,
    "grass_color": 6523989,
    "sky_color": 8827134,
    "water_color": 4159204,
    "water_fog_color": 329011
  },
  "features": [
    [],
    [],
    [],
    [],
    [],
    [],
    [
      "edumia:crystals/elven_crystal",
      "minecraft:disk_clay",
      "minecraft:disk_gravel",
      "minecraft:disk_sand",
      "minecraft:ore_andesite_lower",
      "minecraft:ore_andesite_upper",
      "minecraft:ore_coal_upper",
      "minecraft:ore_diorite_lower",
      "minecraft:ore_diorite_upper",
      "minecraft:ore_dirt",
      "minecraft:ore_granite_lower",
      "minecraft:ore_granite_upper",
      "minecraft:ore_gravel",
      "minecraft:ore_tuff"
    ],
    [],
    [],
    [
      "edumia:boulders/big_limestone_boulder",
      "edumia:boulders/limestone_boulder",
      "edumia:flowers/heather_bush",
      "edumia:tree/oaks/oak/oak_bush_tree",
      "edumia:tree/temperate/birch/super_rare_birch_tree",
      "minecraft:brown_mushroom_normal",
      "minecraft:flower_default",
      "minecraft:glow_lichen",
      "minecraft:grass_bonemeal",
      "minecraft:patch_grass_plain",
      "minecraft:patch_pumpkin",
      "minecraft:patch_sugar_cane",
      "minecraft:red_mushroom_normal"
    ],
    [
      "minecraft:freeze_top_layer"
    ]
  ],
  "has_precipitation": true,
  "spawn_costs": {},
  "spawners": {
    "ambient": [],
    "axolotls": [],
    "creature": [
      {
        "type": "minecraft:sheep",
        "maxCount": 4,
        "minCount": 4,
        "weight": 12
      },
      {
        "type": "minecraft:pig",
        "maxCount": 4,
        "minCount": 4,
        "weight": 10
      },
      {
        "type": "minecraft:chicken",
        "maxCount": 4,
        "minCount": 4,
        "weight": 10
      },
      {
        "type": "minecraft:cow",
        "maxCount": 4,
        "minCount": 4,
        "weight": 8
      },
      {
        "type": "minecraft:sheep",
        "maxCount": 4,
        "minCount": 4,
        "weight": 12
      },
      {
        "type": "minecraft:pig",
        "maxCount": 4,
        "minCount": 4,
        "weight": 10
      },
      {
        "type": "minecraft:chicken",
        "maxCount": 4,
        "minCount": 4,
        "weight": 10
      },
      {
        "type": "minecraft:cow",
        "maxCount": 4,
        "minCount": 4,
        "weight": 8
      },
      {
        "type": "minecraft:donkey",
        "maxCount": 3,
        "minCount": 1,
        "weight": 1
      },
      {
        "type": "minecraft:horse",
        "maxCount": 6,
        "minCount": 2,
        "weight": 5
      }
    ],
    "misc": [],
    "monster": [],
    "underground_water_creature": [],
    "water_ambient": [],
    "water_creature": []
  },
  "temperature": 0.5
}